anqa/core/__init__.py
anqa/core/_version.py
anqa/core/abc/__init__.py
anqa/core/abc/repository.py
anqa/core/abc/runner.py
anqa/core/abc/service.py
anqa/core/cache.py
anqa/core/enum.py
anqa/core/exceptions.py
anqa/core/logger.py
anqa/core/mixins/__init__.py
anqa/core/mixins/builder.py
anqa/core/mixins/func.py
anqa/core/mixins/logger.py
anqa/core/mixins/middleware.py
anqa/core/periodic.py
anqa/core/py.typed
anqa/core/retries.py
anqa/core/schema.py
anqa/core/settings.py
anqa/core/types.py
anqa/core/utils/__init__.py
anqa/core/utils/class_utils.py
anqa/core/utils/dateutil.py
anqa/core/utils/functools.py
anqa/core/utils/imports.py
anqa/core/utils/json.py
anqa_core-0.0.1.dist-info/METADATA
anqa_core-0.0.1.dist-info/WHEEL
anqa_core-0.0.1.dist-info/RECORD
