Metadata-Version: 2.1
Name: anqa-core
Version: 0.0.1
Summary: 
Requires-Python: >=3.8.1,<4.0
Classifier: Programming Language :: Python :: 3
Classifier: Programming Language :: Python :: 3.9
Classifier: Programming Language :: Python :: 3.10
Classifier: Programming Language :: Python :: 3.11
Requires-Dist: orjson (>=3.8.7,<4.0.0)
Requires-Dist: prometheus-client (>=0.16.0,<0.17.0)
Requires-Dist: pydantic (>=1.10.6,<2.0.0)
Requires-Dist: python-json-logger (>=2.0.7,<3.0.0)
Requires-Dist: uvloop (>=0.17.0,<0.18.0)
